requence/__init__.py
requence/consumer.py
requence/context.py
requence/exceptions.py
requence/typing.py
requence/utils.py
requence/version.py
requence-0.2.0.dist-info/METADATA
requence-0.2.0.dist-info/WHEEL
requence-0.2.0.dist-info/top_level.txt
requence-0.2.0.dist-info/RECORD
