Metadata-Version: 2.1
Name: requence
Version: 0.2.0
Summary: Consumer implementation
Author: Torsten Blindert
Requires-Python: >=3.10
Requires-Dist: pika >=1.3.2
Requires-Dist: semver >=3.0.2
